.travis.yml
MANIFEST.in
NOTICE.txt
README.rst
bootstrap.py
buildout.cfg
setup.py
travis.cfg
docs/HISTORY.txt
docs/INSTALL.txt
docs/LICENSE.txt
docs/Protocols.graffle
edrn/__init__.py
edrn.summarizer.egg-info/PKG-INFO
edrn.summarizer.egg-info/SOURCES.txt
edrn.summarizer.egg-info/dependency_links.txt
edrn.summarizer.egg-info/entry_points.txt
edrn.summarizer.egg-info/namespace_packages.txt
edrn.summarizer.egg-info/not-zip-safe
edrn.summarizer.egg-info/requires.txt
edrn.summarizer.egg-info/top_level.txt
edrn/summarizer/README.rst
edrn/summarizer/__init__.py
edrn/summarizer/biomarkersummarizergenerator.py
edrn/summarizer/biomutasummarizergenerator.py
edrn/summarizer/collaborationsummarizergenerator.py
edrn/summarizer/configure.zcml
edrn/summarizer/datasetsummarizergenerator.py
edrn/summarizer/exceptions.py
edrn/summarizer/extresourcesummarizergenerator.py
edrn/summarizer/idsearch.py
edrn/summarizer/interfaces.py
edrn/summarizer/nulljsongenerator.py
edrn/summarizer/publicationsummarizergenerator.py
edrn/summarizer/setuphandlers.py
edrn/summarizer/sitesummarizerupdater.py
edrn/summarizer/specimensummarizergenerator.py
edrn/summarizer/summarizergenerator.py
edrn/summarizer/summarizersource.py
edrn/summarizer/summarizerupdater.py
edrn/summarizer/testing.py
edrn/summarizer/upgrades.py
edrn/summarizer/upgrades.zcml
edrn/summarizer/utils.py
edrn/summarizer/profiles/default/edrn.summarizer.marker.txt
edrn/summarizer/profiles/default/metadata.xml
edrn/summarizer/profiles/default/types.xml
edrn/summarizer/profiles/default/types/edrn.summarizer.biomarkersummarizergenerator.xml
edrn/summarizer/profiles/default/types/edrn.summarizer.biomutasummarizergenerator.xml
edrn/summarizer/profiles/default/types/edrn.summarizer.collaborationsummarizergenerator.xml
edrn/summarizer/profiles/default/types/edrn.summarizer.datasetsummarizergenerator.xml
edrn/summarizer/profiles/default/types/edrn.summarizer.extresourcesummarizergenerator.xml
edrn/summarizer/profiles/default/types/edrn.summarizer.nulljsongenerator.xml
edrn/summarizer/profiles/default/types/edrn.summarizer.publicationsummarizergenerator.xml
edrn/summarizer/profiles/default/types/edrn.summarizer.specimensummarizergenerator.xml
edrn/summarizer/profiles/default/types/edrn.summarizer.summarizersource.xml
