Metadata-Version: 1.1
Name: edrn.summarizer
Version: 0.0.7
Summary: EDRN Summarizer Server
Home-page: https://github.com/EDRN/edrn.summarizer
Author: David Liu
Author-email: david.liu@jpl.nasa.gov
License: ALv2
Keywords: summary summarizer web zope plone cancer bioinformatics detection informatics edrn
Platform: UNKNOWN
Classifier: Development Status :: 4 - Beta
Classifier: Environment :: Web Environment
Classifier: Framework :: Plone
Classifier: Intended Audience :: Healthcare Industry
Classifier: Intended Audience :: Science/Research
Classifier: License :: OSI Approved :: Apache Software License
Classifier: Operating System :: OS Independent
Classifier: Programming Language :: Python
Classifier: Topic :: Internet :: WWW/HTTP
Classifier: Topic :: Scientific/Engineering :: Bio-Informatics
Classifier: Topic :: Software Development :: Libraries :: Python Modules
